feedarchiver/__init__.py
feedarchiver/__main__.py
feedarchiver/archive.py
feedarchiver/feed.py
feedarchiver/formats.py
feedarchiver/utils.py
feedarchiver/version.py
feedarchiver/enclosures/__init__.py
feedarchiver/enclosures/servarr.py
feedarchiver/enclosures/template.py
feedarchiver/tests/__init__.py
feedarchiver/tests/test_archive.py
feedarchiver/tests/test_cli.py
feedarchiver/tests/test_download.py
feedarchiver/tests/test_feed.py
feedarchiver/tests/test_linking.py
feedarchiver/tests/test_urls.py
feed_archiver-2.0.6.dist-info/.gitignore
feed_archiver-2.0.6.dist-info/METADATA
feed_archiver-2.0.6.dist-info/WHEEL
feed_archiver-2.0.6.dist-info/entry_points.txt
feed_archiver-2.0.6.dist-info/top_level.txt
feed_archiver-2.0.6.dist-info/RECORD
