Metadata-Version: 2.1
Name: feed-archiver
Version: 2.0.6
Summary: Archive the full contents of RSS/Atom syndication feeds including enclosures and assets.
Home-page: https://gitlab.com/rpatterson/feed-archiver
Author: Ross Patterson
Author-email: me@rpatterson.net
License: MIT
Keywords: feeds,syndication,rss,atom,podcasts,enclosures
Classifier: Development Status :: 4 - Beta
Classifier: Environment :: Console
Classifier: Intended Audience :: Developers
Classifier: Intended Audience :: System Administrators
Classifier: License :: OSI Approved :: MIT License
Classifier: Natural Language :: English
Classifier: Operating System :: OS Independent
Classifier: Programming Language :: Python :: 3
Classifier: Programming Language :: Python :: 3.10
Classifier: Programming Language :: Python :: 3.11
Classifier: Programming Language :: Python :: 3.9
Classifier: Programming Language :: Python :: 3.8
Classifier: Programming Language :: Python :: 3.7
Classifier: Programming Language :: Python :: 3 :: Only
Classifier: Topic :: Utilities
Requires-Python: >=3.7
Requires-Dist: argcomplete
Requires-Dist: pyyaml
Requires-Dist: lxml
Requires-Dist: feedparser
Requires-Dist: httpx
Requires-Dist: user-agent
Requires-Dist: arrapi
Requires-Dist: tenacity
Requires-Dist: importlib-metadata ; python_version < "3.10"
Requires-Dist: backports.cached-property ; python_version < "3.8"
Provides-Extra: devel
Requires-Dist: coverage ; extra == 'devel'
Requires-Dist: prospector[with_everything] ; extra == 'devel'
Requires-Dist: xenon ; extra == 'devel'
Requires-Dist: rstcheck ; extra == 'devel'
Requires-Dist: reuse (<1.1.0) ; extra == 'devel'
Requires-Dist: black ; extra == 'devel'
Requires-Dist: autoflake ; extra == 'devel'
Requires-Dist: autopep8 ; extra == 'devel'
Requires-Dist: towncrier ; extra == 'devel'
Requires-Dist: build ; extra == 'devel'
Requires-Dist: lxml-stubs ; extra == 'devel'
Requires-Dist: types-requests ; extra == 'devel'
Requires-Dist: types-PyYAML ; extra == 'devel'
Provides-Extra: test
Requires-Dist: respx ; extra == 'test'
Requires-Dist: requests-mock ; extra == 'test'
Requires-Dist: pytest ; extra == 'test'
Requires-Dist: pytest-subtests ; extra == 'test'
Requires-Dist: pip-tools ; extra == 'test'
